[
  {
    "date": "2025-11-21",
    "commitHash": "22cc27b",
    "changeType": "added",
    "pr": 117,
    "prTitle": "Migrate To Markdown File",
    "prAuthor": "adamgfraser",
    "prUrl": "https://github.com/sky-ecosystem/next-gen-atlas/pull/117",
    "reviewCount": 2,
    "approvalCount": 1,
    "summary": "Migrate To Markdown File",
    "description": "As part of join work between Atlas Axis and Core Facilitator teams, this pull request migrates the Atlas from HTML to Markdown. This allows us to express the full hierarchical structure of the Atlas and will support future automations and AI integrations that are under development."
  },
  {
    "date": "2025-11-21",
    "commitHash": "22cc27b",
    "changeType": "added",
    "pr": 117,
    "prTitle": "Migrate To Markdown File",
    "prAuthor": "adamgfraser",
    "prUrl": "https://github.com/sky-ecosystem/next-gen-atlas/pull/117",
    "reviewCount": 2,
    "approvalCount": 1,
    "summary": "Migrate To Markdown File",
    "description": "As part of join work between Atlas Axis and Core Facilitator teams, this pull request migrates the Atlas from HTML to Markdown. This allows us to express the full hierarchical structure of the Atlas and will support future automations and AI integrations that are under development."
  },
  {
    "date": "2026-04-13",
    "commitHash": "3365665",
    "changeType": "modified",
    "diff": [
      [
        "~",
        [
          [
            "=",
            "Only an operator with the"
          ],
          [
            "-",
            " "
          ],
          [
            "+",
            " "
          ],
          [
            "=",
            "relayer"
          ],
          [
            "-",
            " "
          ],
          [
            "+",
            " "
          ],
          [
            "=",
            "role is able to repay vault debt and burn USDS. To do so, they must call the burnUSDS function of the Controller contract on mainnet with the amount of USDS that they wish to burn. Calling this function will carry out the following actions:"
          ]
        ]
      ],
      [
        "=",
        ""
      ],
      [
        "=",
        "- The contract will confirm the relayer status of the operator. If the caller does not have the relayer role the transaction will revert."
      ],
      [
        "~",
        [
          [
            "=",
            "- The contract will increase the available Rate Limit for minting USDS by the amount of USDS being burned. This increase will be limited by the maxAmount parameter in the"
          ],
          [
            "-",
            " "
          ],
          [
            "+",
            " "
          ],
          [
            "=",
            "`Rate Limit`"
          ],
          [
            "-",
            " "
          ],
          [
            "+",
            " "
          ],
          [
            "=",
            "contract."
          ]
        ]
      ],
      [
        "=",
        "- The contract will transfer USDS from the proxy to the buffer."
      ],
      [
        "~",
        [
          [
            "=",
            "- The contract will burn the USDS from the buffer and"
          ],
          [
            "-",
            " "
          ],
          [
            "+",
            " "
          ],
          [
            "=",
            "`wipe`"
          ],
          [
            "-",
            " "
          ],
          [
            "+",
            " "
          ],
          [
            "=",
            "an equivalent amount from the vault's debt."
          ]
        ]
      ],
      [
        "=",
        ""
      ],
      [
        "=",
        "The function call is as follows:"
      ]
    ],
    "pr": 223,
    "prTitle": "remove non breaking space characters",
    "prAuthor": "0xldr",
    "prUrl": "https://github.com/sky-ecosystem/next-gen-atlas/pull/223",
    "reviewCount": 1,
    "approvalCount": 1
  }
]
