[
  {
    "date": "2025-11-21",
    "commitHash": "22cc27b",
    "changeType": "moved",
    "pr": 117,
    "prTitle": "Migrate To Markdown File",
    "prAuthor": "adamgfraser",
    "prUrl": "https://github.com/sky-ecosystem/next-gen-atlas/pull/117",
    "reviewCount": 2,
    "approvalCount": 1,
    "summary": "Migrate To Markdown File",
    "description": "As part of join work between Atlas Axis and Core Facilitator teams, this pull request migrates the Atlas from HTML to Markdown. This allows us to express the full hierarchical structure of the Atlas and will support future automations and AI integrations that are under development."
  },
  {
    "date": "2026-04-02",
    "commitHash": "234f16e",
    "changeType": "removed",
    "diff": [
      [
        "-",
        "Gelato Network"
      ],
      [
        "-",
        ""
      ],
      [
        "-",
        "Budget: 1,500 USDS per day"
      ],
      [
        "-",
        "Stream Duration: 3 years (start date 29 May 2023)."
      ]
    ],
    "pr": 217,
    "prTitle": "Atlas Edit Proposal — 2026-03-30",
    "prAuthor": "adamgfraser",
    "prUrl": "https://github.com/sky-ecosystem/next-gen-atlas/pull/217",
    "reviewCount": 2,
    "approvalCount": 1,
    "commentCount": 1,
    "summary": "Add TechOps Services As Keeper Provider And Remove Deactivated Networks",
    "description": "Adds TechOps Services as a keeper provider operating the SKY lane in dss-cron, removes the deactivated Gelato Network and Keep3r Network documents, and updates the Keepers parent document to better describe keeper responsibilities."
  }
]
